[
  {
    "message_id": "cbb0a08a790a672c",
    "text": "Flipper One – we need your help",
    "source": "https://news.ycombinator.com/item?id=48220647",
    "platform": "hackernews",
    "url": "https://news.ycombinator.com/item?id=48220647",
    "author": "unknown",
    "timestamp": "2026-05-21T16:50:50.606570",
    "language": "en",
    "upvotes": 0,
    "downvotes": 0,
    "replies_count": 0,
    "label": null,
    "annotation_status": "pending",
    "collected_at": "2026-05-21T16:50:50.606570",
    "message_type": "post"
  },
  {
    "message_id": "1599eba75453aa0b",
    "text": "Python 3.15: features that didn't make the headlines",
    "source": "https://news.ycombinator.com/item?id=48220696",
    "platform": "hackernews",
    "url": "https://news.ycombinator.com/item?id=48220696",
    "author": "unknown",
    "timestamp": "2026-05-21T16:50:50.606876",
    "language": "en",
    "upvotes": 0,
    "downvotes": 0,
    "replies_count": 0,
    "label": null,
    "annotation_status": "pending",
    "collected_at": "2026-05-21T16:50:50.606876",
    "message_type": "post"
  },
  {
    "message_id": "881cd47c4dd7ae4b",
    "text": "We're testing new ad formats in Search and expanding our Direct Offers pilot",
    "source": "https://news.ycombinator.com/item?id=48220105",
    "platform": "hackernews",
    "url": "https://news.ycombinator.com/item?id=48220105",
    "author": "unknown",
    "timestamp": "2026-05-21T16:50:50.607126",
    "language": "en",
    "upvotes": 0,
    "downvotes": 0,
    "replies_count": 0,
    "label": null,
    "annotation_status": "pending",
    "collected_at": "2026-05-21T16:50:50.607126",
    "message_type": "post"
  },
  {
    "message_id": "499da37beede4aa7",
    "text": "Michael Keating has died",
    "source": "https://news.ycombinator.com/item?id=48223303",
    "platform": "hackernews",
    "url": "https://news.ycombinator.com/item?id=48223303",
    "author": "unknown",
    "timestamp": "2026-05-21T16:50:50.607279",
    "language": "en",
    "upvotes": 0,
    "downvotes": 0,
    "replies_count": 0,
    "label": null,
    "annotation_status": "pending",
    "collected_at": "2026-05-21T16:50:50.607279",
    "message_type": "post"
  },
  {
    "message_id": "99c8b617fc7d9ae3",
    "text": "Lost Images from the 1945 Trinity Nuclear Test Restored",
    "source": "https://news.ycombinator.com/item?id=48220639",
    "platform": "hackernews",
    "url": "https://news.ycombinator.com/item?id=48220639",
    "author": "unknown",
    "timestamp": "2026-05-21T16:50:50.607499",
    "language": "en",
    "upvotes": 0,
    "downvotes": 0,
    "replies_count": 0,
    "label": null,
    "annotation_status": "pending",
    "collected_at": "2026-05-21T16:50:50.607499",
    "message_type": "post"
  },
  {
    "message_id": "11b12ef4c10832fc",
    "text": "Indexing a year of video locally on a 2021 MacBook with Gemma4-31B (50GB swap)",
    "source": "https://news.ycombinator.com/item?id=48222733",
    "platform": "hackernews",
    "url": "https://news.ycombinator.com/item?id=48222733",
    "author": "unknown",
    "timestamp": "2026-05-21T16:50:50.607779",
    "language": "en",
    "upvotes": 0,
    "downvotes": 0,
    "replies_count": 0,
    "label": null,
    "annotation_status": "pending",
    "collected_at": "2026-05-21T16:50:50.607779",
    "message_type": "post"
  },
  {
    "message_id": "3648196e092733d9",
    "text": "Who Wins and Who Loses in Prediction Markets? Evidence from Polymarket",
    "source": "https://news.ycombinator.com/item?id=48221877",
    "platform": "hackernews",
    "url": "https://news.ycombinator.com/item?id=48221877",
    "author": "unknown",
    "timestamp": "2026-05-21T16:50:50.608020",
    "language": "en",
    "upvotes": 0,
    "downvotes": 0,
    "replies_count": 0,
    "label": null,
    "annotation_status": "pending",
    "collected_at": "2026-05-21T16:50:50.608020",
    "message_type": "post"
  },
  {
    "message_id": "0edeab18586f3e94",
    "text": "FatGid: FreeBSD 14.x kernel local privilege escalation",
    "source": "https://news.ycombinator.com/item?id=48221415",
    "platform": "hackernews",
    "url": "https://news.ycombinator.com/item?id=48221415",
    "author": "unknown",
    "timestamp": "2026-05-21T16:50:50.608295",
    "language": "en",
    "upvotes": 0,
    "downvotes": 0,
    "replies_count": 0,
    "label": null,
    "annotation_status": "pending",
    "collected_at": "2026-05-21T16:50:50.608295",
    "message_type": "post"
  },
  {
    "message_id": "d87d40dcdc034a9f",
    "text": "Google's Antigravity Bait and Switch",
    "source": "https://news.ycombinator.com/item?id=48222529",
    "platform": "hackernews",
    "url": "https://news.ycombinator.com/item?id=48222529",
    "author": "unknown",
    "timestamp": "2026-05-21T16:50:50.608548",
    "language": "en",
    "upvotes": 0,
    "downvotes": 0,
    "replies_count": 0,
    "label": null,
    "annotation_status": "pending",
    "collected_at": "2026-05-21T16:50:50.608548",
    "message_type": "post"
  },
  {
    "message_id": "b3b4a4b8b3c66809",
    "text": "AI is just unauthorised plagiarism at a bigger scale",
    "source": "https://news.ycombinator.com/item?id=48222383",
    "platform": "hackernews",
    "url": "https://news.ycombinator.com/item?id=48222383",
    "author": "unknown",
    "timestamp": "2026-05-21T16:50:50.608812",
    "language": "en",
    "upvotes": 0,
    "downvotes": 0,
    "replies_count": 0,
    "label": null,
    "annotation_status": "pending",
    "collected_at": "2026-05-21T16:50:50.608812",
    "message_type": "post"
  },
  {
    "message_id": "377321bb8f91ed93",
    "text": "Show HN: Rmux – A programmable terminal multiplexer with a Playwright-style SDK",
    "source": "https://news.ycombinator.com/item?id=48219918",
    "platform": "hackernews",
    "url": "https://news.ycombinator.com/item?id=48219918",
    "author": "unknown",
    "timestamp": "2026-05-21T16:50:50.609121",
    "language": "en",
    "upvotes": 0,
    "downvotes": 0,
    "replies_count": 0,
    "label": null,
    "annotation_status": "pending",
    "collected_at": "2026-05-21T16:50:50.609121",
    "message_type": "post"
  },
  {
    "message_id": "81ff4d4d318db9a0",
    "text": "GitHub confirms breach of 3,800 repos via malicious VSCode extension",
    "source": "https://news.ycombinator.com/item?id=48207660",
    "platform": "hackernews",
    "url": "https://news.ycombinator.com/item?id=48207660",
    "author": "unknown",
    "timestamp": "2026-05-21T16:50:50.609329",
    "language": "en",
    "upvotes": 0,
    "downvotes": 0,
    "replies_count": 0,
    "label": null,
    "annotation_status": "pending",
    "collected_at": "2026-05-21T16:50:50.609329",
    "message_type": "post"
  },
  {
    "message_id": "65bc3c0b73c7aebe",
    "text": "Vivaldi 8.0",
    "source": "https://news.ycombinator.com/item?id=48219060",
    "platform": "hackernews",
    "url": "https://news.ycombinator.com/item?id=48219060",
    "author": "unknown",
    "timestamp": "2026-05-21T16:50:50.609495",
    "language": "en",
    "upvotes": 0,
    "downvotes": 0,
    "replies_count": 0,
    "label": null,
    "annotation_status": "pending",
    "collected_at": "2026-05-21T16:50:50.609495",
    "message_type": "post"
  },
  {
    "message_id": "a55264ae4461e657",
    "text": "Cekura (YC F24) Is Hiring",
    "source": "https://news.ycombinator.com/item?id=48221230",
    "platform": "hackernews",
    "url": "https://news.ycombinator.com/item?id=48221230",
    "author": "unknown",
    "timestamp": "2026-05-21T16:50:50.609709",
    "language": "en",
    "upvotes": 0,
    "downvotes": 0,
    "replies_count": 0,
    "label": null,
    "annotation_status": "pending",
    "collected_at": "2026-05-21T16:50:50.609709",
    "message_type": "post"
  },
  {
    "message_id": "932740a6dfd899fc",
    "text": "Get your passwords out of Bitwarden while you still can",
    "source": "https://news.ycombinator.com/item?id=48223258",
    "platform": "hackernews",
    "url": "https://news.ycombinator.com/item?id=48223258",
    "author": "unknown",
    "timestamp": "2026-05-21T16:50:50.609927",
    "language": "en",
    "upvotes": 0,
    "downvotes": 0,
    "replies_count": 0,
    "label": null,
    "annotation_status": "pending",
    "collected_at": "2026-05-21T16:50:50.609927",
    "message_type": "post"
  },
  {
    "message_id": "4664d3623a551055",
    "text": "Mounting Git commits as folders with NFS",
    "source": "https://news.ycombinator.com/item?id=48190373",
    "platform": "hackernews",
    "url": "https://news.ycombinator.com/item?id=48190373",
    "author": "unknown",
    "timestamp": "2026-05-21T16:50:50.610148",
    "language": "en",
    "upvotes": 0,
    "downvotes": 0,
    "replies_count": 0,
    "label": null,
    "annotation_status": "pending",
    "collected_at": "2026-05-21T16:50:50.610148",
    "message_type": "post"
  },
  {
    "message_id": "21fa62ed0f59e606",
    "text": "IBM invented semiconductor manufacturing automation",
    "source": "https://news.ycombinator.com/item?id=48220446",
    "platform": "hackernews",
    "url": "https://news.ycombinator.com/item?id=48220446",
    "author": "unknown",
    "timestamp": "2026-05-21T16:50:50.610352",
    "language": "en",
    "upvotes": 0,
    "downvotes": 0,
    "replies_count": 0,
    "label": null,
    "annotation_status": "pending",
    "collected_at": "2026-05-21T16:50:50.610352",
    "message_type": "post"
  },
  {
    "message_id": "4075ff604a206376",
    "text": "A Bipartisan Amendment Would End Police License Plate Tracking Nationwide",
    "source": "https://news.ycombinator.com/item?id=48221915",
    "platform": "hackernews",
    "url": "https://news.ycombinator.com/item?id=48221915",
    "author": "unknown",
    "timestamp": "2026-05-21T16:50:50.610652",
    "language": "en",
    "upvotes": 0,
    "downvotes": 0,
    "replies_count": 0,
    "label": null,
    "annotation_status": "pending",
    "collected_at": "2026-05-21T16:50:50.610652",
    "message_type": "post"
  },
  {
    "message_id": "80ee8d8071cf25ec",
    "text": "Magic the Gathering format: Fun 40 (2025)",
    "source": "https://news.ycombinator.com/item?id=48222105",
    "platform": "hackernews",
    "url": "https://news.ycombinator.com/item?id=48222105",
    "author": "unknown",
    "timestamp": "2026-05-21T16:50:50.610866",
    "language": "en",
    "upvotes": 0,
    "downvotes": 0,
    "replies_count": 0,
    "label": null,
    "annotation_status": "pending",
    "collected_at": "2026-05-21T16:50:50.610866",
    "message_type": "post"
  },
  {
    "message_id": "47c0c3d142bbe9d7",
    "text": "Show HN: I Dedicated 4 Years to Mastering Offline Password Cracking",
    "source": "https://news.ycombinator.com/item?id=48221896",
    "platform": "hackernews",
    "url": "https://news.ycombinator.com/item?id=48221896",
    "author": "unknown",
    "timestamp": "2026-05-21T16:50:50.611053",
    "language": "en",
    "upvotes": 0,
    "downvotes": 0,
    "replies_count": 0,
    "label": null,
    "annotation_status": "pending",
    "collected_at": "2026-05-21T16:50:50.611053",
    "message_type": "post"
  }
]